[
    {
        "title": "Yeh Raaten Yeh Mausam - Lofi",
        "artist": "Kishore Kumar, Asha Bhosle",
        "file": "Audio/Yeh Raaten Yeh Mausam - Lofi.mp3",
        "image": "Thumbnails/Yeh Raaten Yeh Mausam - Lofi_thumbnail.jpg",
        "ext": ""
    },
    {
        "title": "Tumse Milke Aisa Laga Tumse Milke",
        "artist": "Asha Bhosle, Suresh Wadkar",
        "file": "Audio/Tumse Milke _ Asha Bhosle _ Suresh Wadkar _ Parinda _ Bollywood Song _ 1989.mp3",
        "image": "Thumbnails/Tumse Milke _ Asha Bhosle _ Suresh Wadkar _ Parinda _ Bollywood Song _ 1989_thumbnail.jpg",
        "ext": ""
    },
    {
        "title": "Inteha Ho Gayi Intezaar Ki",
        "artist": "Asha Bhosle",
        "file": "Audio/Inteha Ho Gayi Intezaar Ki _ Sharaabi _ Amitabh Bachan, Jaya Prada _ Asha Bhosle, Kishore Kumar.mp3",
        "image": "Thumbnails/Inteha Ho Gayi Intezaar Ki _ Sharaabi _ Amitabh Bachan, Jaya Prada _ Asha Bhosle, Kishore Kumar_thumbnail.jpg",
        "ext": ""
    },
    {
        "title": "Chura Liya Hai Tumne Jo Dil Ko",
        "artist": "Asha Bhosle",
        "file": "Audio/Chura Liya Hai Tumne Jo Dil Ko ｜ Lyrical ｜ Zeenat Aman ｜ Asha Bhosle [XuCp0r3vhPQ].mp3",
        "image": "Thumbnails/Chura Liya Hai Tumne Jo Dil Ko ｜ Lyrical ｜ Zeenat Aman ｜ Asha Bhosle [XuCp0r3vhPQ]_thumbnail.jpg",
        "ext": ""
    },
    {
        "title": "In Akhon Ki Masti Ke",
        "artist": "Asha Bhosle",
        "file": "Audio/In Akhon Ki Masti Ke ｜ Asha Bhosle ｜ Lyrical Video ｜ Rekha Songs ｜ Umrao Jaan ｜ Ghazal Romantic [KjJWcs3uo6k].mp3",
        "image": "Thumbnails/In Akhon Ki Masti Ke ｜ Asha Bhosle ｜ Lyrical Video ｜ Rekha Songs ｜ Umrao Jaan ｜ Ghazal Romantic [KjJWcs3uo6k]_thumbnail.jpg",
        "ext": ""
    }
]